td_google_login/__init__.py
td_google_login/admin.py
td_google_login/apps.py
td_google_login/models.py
td_google_login/settings.py
td_google_login/signals.py
td_google_login/urls.py
td_google_login/utils.py
td_google_login/views.py
td_google_login/management/__init__.py
td_google_login/management/commands/__init__.py
td_google_login/management/commands/cleanup_oauth_states.py
td_google_login/migrations/__init__.py
td_google_login-1.0.0.dist-info/licenses/LICENSE
td_google_login-1.0.0.dist-info/METADATA
td_google_login-1.0.0.dist-info/WHEEL
td_google_login-1.0.0.dist-info/top_level.txt
td_google_login-1.0.0.dist-info/RECORD
