Metadata-Version: 2.4
Name: td-google-login
Version: 1.0.0
Summary: A plug-and-play Django package for Google OAuth 2.0 authentication
Home-page: https://github.com/darshan-tbd/td-google-login
Author: TD Solutions
Author-email: TD Solutions <support@tdsolutions.com>
License: MIT
Project-URL: Homepage, https://github.com/darshan-tbd/td-google-login
Project-URL: Repository, https://github.com/darshan-tbd/td-google-login
Project-URL: Documentation, https://github.com/darshan-tbd/td-google-login#readme
Project-URL: Bug Tracker, https://github.com/darshan-tbd/td-google-login/issues
Keywords: django,google,oauth,authentication,login
Classifier: Development Status :: 5 - Production/Stable
Classifier: Intended Audience :: Developers
Classifier: License :: OSI Approved :: MIT License
Classifier: Operating System :: OS Independent
Classifier: Programming Language :: Python :: 3
Classifier: Programming Language :: Python :: 3.8
Classifier: Programming Language :: Python :: 3.9
Classifier: Programming Language :: Python :: 3.10
Classifier: Programming Language :: Python :: 3.11
Classifier: Programming Language :: Python :: 3.12
Classifier: Framework :: Django
Classifier: Framework :: Django :: 3.2
Classifier: Framework :: Django :: 4.0
Classifier: Framework :: Django :: 4.1
Classifier: Framework :: Django :: 4.2
Classifier: Framework :: Django :: 5.0
Requires-Python: >=3.8
License-File: LICENSE
Requires-Dist: Django>=3.2
Requires-Dist: google-auth>=2.0.0
Requires-Dist: google-auth-oauthlib>=0.8.0
Requires-Dist: google-auth-httplib2>=0.1.0
Requires-Dist: requests>=2.25.0
Provides-Extra: dev
Requires-Dist: pytest>=6.0; extra == "dev"
Requires-Dist: pytest-django>=4.0; extra == "dev"
Requires-Dist: black>=22.0; extra == "dev"
Requires-Dist: flake8>=4.0; extra == "dev"
Requires-Dist: mypy>=0.950; extra == "dev"
Dynamic: author
Dynamic: home-page
Dynamic: license-file
Dynamic: requires-python
